LICENSE.md
README.md
pyproject.toml
src/ewoksscxrd/__init__.py
src/ewoksscxrd.egg-info/PKG-INFO
src/ewoksscxrd.egg-info/SOURCES.txt
src/ewoksscxrd.egg-info/dependency_links.txt
src/ewoksscxrd.egg-info/entry_points.txt
src/ewoksscxrd.egg-info/requires.txt
src/ewoksscxrd.egg-info/top_level.txt
src/ewoksscxrd/tasks/__init__.py
src/ewoksscxrd/tasks/averageframes.py
src/ewoksscxrd/tasks/createinifiles.py
src/ewoksscxrd/tasks/createparfiles.py
src/ewoksscxrd/tasks/createrunfiles.py
src/ewoksscxrd/tasks/createsetccdfiles.py
src/ewoksscxrd/tasks/dataportal.py
src/ewoksscxrd/tasks/eiger2crysalis.py
src/ewoksscxrd/tasks/lima2thresholding.py
src/ewoksscxrd/tasks/tifffiles.py
src/ewoksscxrd/tasks/utils.py
src/ewoksscxrd/tests/__init__.py
src/ewoksscxrd/tests/test_averageframes.py
src/ewoksscxrd/tests/test_createinifiles.py
src/ewoksscxrd/tests/test_createparfiles.py
src/ewoksscxrd/tests/test_createrunfiles.py
src/ewoksscxrd/tests/test_createsetccdfiles.py
src/ewoksscxrd/tests/test_dataportal.py
src/ewoksscxrd/tests/test_eiger2crysalis.py
src/ewoksscxrd/tests/test_tifffiles.py
src/ewoksscxrd/tests/test_utils.py
src/ewoksscxrd/tests/data/__init__.py
src/ewoksscxrd/tests/data/eiger_0000.h5
src/ewoksscxrd/tests/data/frame_1_1.esperanto