Metadata-Version: 2.4
Name: ewoksscxrd
Version: 0.5.5
Summary: Ewoks SC-XRD workflows
Author-email: ESRF <dau-pydev@esrf.fr>
License: # MIT License
Project-URL: Homepage, https://gitlab.esrf.fr/workflow/ewoksapps/ewoksscxrd/
Project-URL: Documentation, https://ewoksscxrd.readthedocs.io/
Project-URL: Repository, https://gitlab.esrf.fr/workflow/ewoksapps/ewoksscxrd/
Project-URL: Issues, https://gitlab.esrf.fr/workflow/ewoksapps/ewoksscxrd/issues
Project-URL: Changelog, https://gitlab.esrf.fr/workflow/ewoksapps/ewoksscxrd/-/blob/main/CHANGELOG.md
Keywords: ewoks
Classifier: Intended Audience :: Science/Research
Classifier: License :: OSI Approved :: MIT License
Classifier: Programming Language :: Python :: 3
Requires-Python: >=3.8
License-File: LICENSE.md
Requires-Dist: numexpr
Requires-Dist: fabio
Requires-Dist: ewoks
Requires-Dist: cryio
Requires-Dist: silx
Requires-Dist: pyicat-plus
Provides-Extra: test
Requires-Dist: pytest>=7; extra == "test"
Requires-Dist: pyqt5; extra == "test"
Provides-Extra: dev
Requires-Dist: ewoksscxrd[test]; extra == "dev"
Requires-Dist: black>=25; extra == "dev"
Requires-Dist: flake8>=4; extra == "dev"
Provides-Extra: doc
Requires-Dist: ewoksscxrd[test]; extra == "doc"
Requires-Dist: sphinx>=4.5; extra == "doc"
Requires-Dist: sphinx-autodoc-typehints>=1.16; extra == "doc"
Requires-Dist: pydata_sphinx_theme; extra == "doc"
Dynamic: license-file
